xminigrid/__init__.py
xminigrid/benchmarks.py
xminigrid/environment.py
xminigrid/manual_control.py
xminigrid/py.typed
xminigrid/registration.py
xminigrid/types.py
xminigrid/wrappers.py
xminigrid/core/actions.py
xminigrid/core/constants.py
xminigrid/core/goals.py
xminigrid/core/grid.py
xminigrid/core/observation.py
xminigrid/core/rules.py
xminigrid/envs/__init__.py
xminigrid/envs/xland.py
xminigrid/envs/minigrid/blockedunlockpickup.py
xminigrid/envs/minigrid/doorkey.py
xminigrid/envs/minigrid/empty.py
xminigrid/envs/minigrid/fourrooms.py
xminigrid/envs/minigrid/lockedroom.py
xminigrid/envs/minigrid/memory.py
xminigrid/envs/minigrid/playground.py
xminigrid/envs/minigrid/unlock.py
xminigrid/envs/minigrid/unlockpickup.py
xminigrid/experimental/img_obs.py
xminigrid/rendering/rgb_render.py
xminigrid/rendering/text_render.py
xminigrid/rendering/utils.py
xminigrid-0.9.3.dist-info/licenses/LICENSE
xminigrid-0.9.3.dist-info/METADATA
xminigrid-0.9.3.dist-info/WHEEL
xminigrid-0.9.3.dist-info/top_level.txt
xminigrid-0.9.3.dist-info/RECORD
