Metadata-Version: 2.4
Name: xminigrid
Version: 0.9.3
Summary: JAX-accelerated meta-reinforcement learning environments inspired by XLand and MiniGrid
Author-email: Alexander Nikulin <hsehowuhh@gmail.com>
License:                                  Apache License
Keywords: jax,neural-networks,deep-learning,reinforcement learning,meta reinforcement learning,gridworld,minigrid,xland
Classifier: Development Status :: 3 - Alpha
Classifier: Intended Audience :: Developers
Classifier: Intended Audience :: Science/Research
Classifier: Natural Language :: English
Classifier: Programming Language :: Python
Classifier: Programming Language :: Python :: 3
Classifier: Programming Language :: Python :: 3.9
Classifier: Programming Language :: Python :: 3.10
Classifier: Topic :: Scientific/Engineering :: Artificial Intelligence
Classifier: License :: OSI Approved :: Apache Software License
Requires-Python: >=3.9
License-File: LICENSE
Requires-Dist: jax>=0.4.27
Requires-Dist: jaxlib>=0.4.27
Requires-Dist: flax>=0.8.0
Requires-Dist: rich>=13.4.2
Requires-Dist: tqdm>=4.67.1
Requires-Dist: chex>=0.1.85
Requires-Dist: imageio>=2.31.2
Requires-Dist: imageio-ffmpeg>=0.4.9
Provides-Extra: dev
Requires-Dist: ruff>=0.1.6; extra == "dev"
Requires-Dist: pre-commit>=3.3.3; extra == "dev"
Requires-Dist: pyright>=1.1.347; extra == "dev"
Provides-Extra: baselines
Requires-Dist: matplotlib>=3.7.2; extra == "baselines"
Requires-Dist: wandb>=0.15.10; extra == "baselines"
Requires-Dist: pyrallis>=0.3.1; extra == "baselines"
Requires-Dist: distrax>=0.1.4; extra == "baselines"
Requires-Dist: optax>=0.1.5; extra == "baselines"
Requires-Dist: orbax>=0.1.9; extra == "baselines"
Requires-Dist: tqdm>=4.66.4; extra == "baselines"
Dynamic: license-file
